MegaLiveInstantActionPlotterDeluxe/PlotImplementations.py
MegaLiveInstantActionPlotterDeluxe/__init__.py
MegaLiveInstantActionPlotterDeluxe/pyqt_live_plotter.py
MegaLiveInstantActionPlotterDeluxe/pyqt_liveplotter_creatorconnector.py
MegaLiveInstantActionPlotterDeluxe-0.0.1.dist-info/LICENSE
MegaLiveInstantActionPlotterDeluxe-0.0.1.dist-info/METADATA
MegaLiveInstantActionPlotterDeluxe-0.0.1.dist-info/WHEEL
MegaLiveInstantActionPlotterDeluxe-0.0.1.dist-info/top_level.txt
MegaLiveInstantActionPlotterDeluxe-0.0.1.dist-info/RECORD
