Metadata-Version: 2.1
Name: MegaLiveInstantActionPlotterDeluxe
Version: 0.0.1
Summary: A small python liveplotter using PyQtGraph
Home-page: https://github.com/JakobWe/MegaLiveInstantActionPlotterDeluxe
Author: Jakob Weimar
Author-email: jakob.weimar@gmx.de
License: UNKNOWN
Platform: UNKNOWN
Classifier: Programming Language :: Python :: 3
Classifier: License :: OSI Approved :: GNU General Public License v3 (GPLv3)
Classifier: Operating System :: OS Independent
Requires-Python: >=3.6
Requires-Dist: pyqtgraph (>=0.10.0)
